README.rst
other.py
setup.py
other.egg-info/PKG-INFO
other.egg-info/SOURCES.txt
other.egg-info/dependency_links.txt
other.egg-info/requires.txt
other.egg-info/top_level.txt