Metadata-Version: 1.0
Name: other
Version: 1.0.0
Summary: The Zen of Zope, by Alex Clark
Home-page: https://github.com/aclark4life/other
Author: Alex Clark
Author-email: aclark@aclark.net
License: UNKNOWN
Platform: UNKNOWN
